misc/moo.mp3
misc/success.mp3
T-reX/CustomConfig.py
T-reX/ExchangeEditor.py
T-reX/ExplodeDatabase.py
T-reX/FutureScenarios.py
T-reX/MakeCustomDatabase.py
T-reX/MethodEditor.py
T-reX/SearchMaterial.py
T-reX/SearchWaste.py
T-reX/VerifyDatabase.py
T-reX/__init__.py
T-reX/config/__init__.py
T-reX/config/queries_materials.py
T-reX/config/queries_waste.py
T-reX/config/user_settings.py
T-reX/config_backup/__init__.py
T-reX/config_backup/queries_materials.py
T-reX/config_backup/queries_waste.py
T-reX/config_backup/user_settings.py
T-reX/main.py
tests/test-import.py
tests/test-verify.py
t_rex_lca-0.2.2.dist-info/LICENSE
t_rex_lca-0.2.2.dist-info/METADATA
t_rex_lca-0.2.2.dist-info/WHEEL
t_rex_lca-0.2.2.dist-info/RECORD
