Metadata-Version: 2.1
Name: T_reX_LCA
Version: 0.2.2
Summary: A tool for analysing waste and material footprints in Life Cycle Assessment (LCA) databases
License: CC0 1.0 Universal (CC0 1.0) Public Domain Dedication
Author: Stewart Charles McDowall
Author-email: s.c.mcdowall@cml.leidenuniv.nl
Requires-Python: >=3.10,<3.12
Classifier: Development Status :: 5 - Production/Stable
Classifier: Intended Audience :: Science/Research
Classifier: License :: CC0 1.0 Universal (CC0 1.0) Public Domain Dedication
Classifier: License :: Other/Proprietary License
Classifier: Operating System :: OS Independent
Classifier: Programming Language :: Python :: 3
Classifier: Programming Language :: Python :: 3.10
Classifier: Programming Language :: Python :: 3.11
Classifier: Topic :: Scientific/Engineering
Requires-Dist: brightway2 (>=2.4.6,<3.0.0)
Requires-Dist: cowsay (>=6.1,<7.0)
Requires-Dist: premise (>=2.0.2,<3.0.0)
Project-URL: documentation, https://T-reX.readthedocs.io/en/latest/
Project-URL: homepage, https://github.com/Stew-McD/T-reX
